[
  {"brand": "케미", "unitType": "안경렌즈 RX", "productType": "안경렌즈 RX", "productName": "1.56 착색", "mainProductName": "착색", "refractiveIndex": "1.56", "options": "1.56 착색", "sellingPrice": "6,000", "status": "사용"},
  {"brand": "케미", "unitType": "안경렌즈 여벌", "productType": "안경렌즈 여벌", "productName": "[케미 근적외선] 1.74", "mainProductName": "근적외선IR", "refractiveIndex": "1.74", "options": "1.74", "sellingPrice": "15,000", "status": "사용"},
  {"brand": "케미", "unitType": "안경렌즈 여벌", "productType": "안경렌즈 여벌", "productName": "[케미 근적외선] 고", "mainProductName": "근적외선IR", "refractiveIndex": "1.60", "options": "고", "sellingPrice": "4,950", "status": "사용"},
  {"brand": "케미", "unitType": "안경렌즈 여벌", "productType": "안경렌즈 여벌", "productName": "[케미 근적외선] 고비", "mainProductName": "근적외선IR", "refractiveIndex": "1.60", "options": "고비", "sellingPrice": "6,200", "status": "사용"},
  {"brand": "케미", "unitType": "안경렌즈 여벌", "productType": "안경렌즈 여벌", "productName": "[케미 근적외선] 중", "mainProductName": "근적외선IR", "refractiveIndex": "1.56", "options": "중", "sellingPrice": "3,300", "status": "사용"},
  {"brand": "케미", "unitType": "안경렌즈 여벌", "productType": "안경렌즈 여벌", "productName": "[케미 근적외선] 중비", "mainProductName": "근적외선IR", "refractiveIndex": "1.56", "options": "중비", "sellingPrice": "4,200", "status": "사용"},
  {"brand": "케미", "unitType": "안경렌즈 여벌", "productType": "안경렌즈 여벌", "productName": "[케미 근적외선] 초고비", "mainProductName": "근적외선IR", "refractiveIndex": "1.67", "options": "초고비", "sellingPrice": "8,000", "status": "사용"},
  {"brand": "케미", "unitType": "안경렌즈 여벌", "productType": "안경렌즈 여벌", "productName": "[케미 누진] 스타일 1.56 L", "mainProductName": "스타일 누진", "refractiveIndex": "1.56", "options": "1.56 누진여벌 왼쪽", "sellingPrice": "4,750", "status": "사용"},
  {"brand": "케미", "unitType": "안경렌즈 여벌", "productType": "안경렌즈 여벌", "productName": "[케미 누진] 스타일 1.56 R", "mainProductName": "스타일 누진", "refractiveIndex": "1.56", "options": "1.56 누진여벌 오른쪽", "sellingPrice": "4,750", "status": "사용"},
  {"brand": "케미", "unitType": "안경렌즈 여벌", "productType": "안경렌즈 여벌", "productName": "[케미 누진] 스타일 1.60 L", "mainProductName": "스타일 누진", "refractiveIndex": "1.60", "options": "1.60 여벌누진 왼쪽", "sellingPrice": "15,000", "status": "사용"},
  {"brand": "케미", "unitType": "안경렌즈 여벌", "productType": "안경렌즈 여벌", "productName": "[케미 누진] 스타일 1.60 R", "mainProductName": "스타일 누진", "refractiveIndex": "1.60", "options": "1.60 여벌누진 오른쪽", "sellingPrice": "15,000", "status": "사용"},
  {"brand": "케미", "unitType": "안경렌즈 여벌", "productType": "안경렌즈 여벌", "productName": "[케미 드라이브] 1.60 ASP", "mainProductName": "X-드라이브", "refractiveIndex": "1.60", "options": "1.60 비구면", "sellingPrice": "6,500", "status": "사용"},
  {"brand": "케미", "unitType": "안경렌즈 여벌", "productType": "안경렌즈 여벌", "productName": "[케미 드라이브] 1.67 ASP", "mainProductName": "X-드라이브", "refractiveIndex": "1.67", "options": "1.67 비구면", "sellingPrice": "9,000", "status": "사용"},
  {"brand": "케미", "unitType": "안경렌즈 여벌", "productType": "안경렌즈 여벌", "productName": "[케미 변색] GEN 8(B)", "mainProductName": "케미변색", "refractiveIndex": "1.60", "options": "GEN 8 (B) 고", "sellingPrice": "42,500", "status": "사용"},
  {"brand": "케미", "unitType": "안경렌즈 여벌", "productType": "안경렌즈 여벌", "productName": "[케미 변색] GEN 8(G)", "mainProductName": "케미변색", "refractiveIndex": "1.60", "options": "GEN 8 (G) 고", "sellingPrice": "42,500", "status": "사용"},
  {"brand": "케미", "unitType": "안경렌즈 여벌", "productType": "안경렌즈 여벌", "productName": "[케미 변색] 고비 클래식(B)", "mainProductName": "케미변색", "refractiveIndex": "1.60", "options": "클래식(B) 고비", "sellingPrice": "24,500", "status": "사용"},
  {"brand": "케미", "unitType": "안경렌즈 여벌", "productType": "안경렌즈 여벌", "productName": "[케미 변색] 고비 클래식(G)", "mainProductName": "케미변색", "refractiveIndex": "1.60", "options": "클래식(G) 고비", "sellingPrice": "24,500", "status": "사용"},
  {"brand": "케미", "unitType": "안경렌즈 여벌", "productType": "안경렌즈 여벌", "productName": "[케미 변색] 엑스트라엑티브(B)", "mainProductName": "케미변색", "refractiveIndex": "1.60", "options": "엑스트라엑티브(B) 고", "sellingPrice": "47,500", "status": "사용"},
  {"brand": "케미", "unitType": "안경렌즈 여벌", "productType": "안경렌즈 여벌", "productName": "[케미 변색] 엑스트라엑티브(G)", "mainProductName": "케미변색", "refractiveIndex": "1.60", "options": "엑스트라엑티브(G) 고", "sellingPrice": "47,500", "status": "사용"},
  {"brand": "케미", "unitType": "안경렌즈 여벌", "productType": "안경렌즈 여벌", "productName": "[케미 변색] 원앤원 (B)", "mainProductName": "케미변색", "refractiveIndex": "1.56", "options": "원앤원 (B) 중비", "sellingPrice": "7,000", "status": "사용"},
  {"brand": "케미", "unitType": "안경렌즈 여벌", "productType": "안경렌즈 여벌", "productName": "[케미 변색] 원앤원 (G)", "mainProductName": "케미변색", "refractiveIndex": "1.56", "options": "원앤원 (G) 중비", "sellingPrice": "7,000", "status": "사용"},
  {"brand": "케미", "unitType": "안경렌즈 여벌", "productType": "안경렌즈 여벌", "productName": "[케미 변색] 중비트랜지션(B)", "mainProductName": "케미변색", "refractiveIndex": "1.56", "options": "클래식(B) 중비", "sellingPrice": "15,500", "status": "사용"},
  {"brand": "케미", "unitType": "안경렌즈 여벌", "productType": "안경렌즈 여벌", "productName": "[케미 변색] 중비트랜지션(G)", "mainProductName": "케미변색", "refractiveIndex": "1.56", "options": "클래식(G) 중비", "sellingPrice": "15,500", "status": "사용"},
  {"brand": "케미", "unitType": "안경렌즈 여벌", "productType": "안경렌즈 여벌", "productName": "[케미 변색] 포토에이드 1.60(B)", "mainProductName": "케미변색", "refractiveIndex": "1.60", "options": "포토에이드(B) 고비", "sellingPrice": "18,900", "status": "사용"},
  {"brand": "케미", "unitType": "안경렌즈 여벌", "productType": "안경렌즈 여벌", "productName": "[케미 변색] 포토에이드 1.60(G)", "mainProductName": "케미변색", "refractiveIndex": "1.60", "options": "포토에이드(G) 고비", "sellingPrice": "18,900", "status": "사용"},
  {"brand": "케미", "unitType": "안경렌즈 여벌", "productType": "안경렌즈 여벌", "productName": "[케미 변색] 포토에이드 1.67(B)", "mainProductName": "케미변색", "refractiveIndex": "1.67", "options": "포토에이드(B) 초고", "sellingPrice": "27,500", "status": "사용"},
  {"brand": "케미", "unitType": "안경렌즈 여벌", "productType": "안경렌즈 여벌", "productName": "[케미 변색] 포토에이드 1.67(G)", "mainProductName": "케미변색", "refractiveIndex": "1.67", "options": "포토에이드(G) 초고", "sellingPrice": "27,500", "status": "사용"},
  {"brand": "케미", "unitType": "안경렌즈 여벌", "productType": "안경렌즈 여벌", "productName": "[케미 변색] 포토에이드 1.74(G)", "mainProductName": "케미변색", "refractiveIndex": "1.74", "options": "174 포토에이드(G)", "sellingPrice": "49,000", "status": "사용"},
  {"brand": "케미", "unitType": "안경렌즈 여벌", "productType": "안경렌즈 여벌", "productName": "[케미 아토메가] 1.67 ASP", "mainProductName": "아토메가", "refractiveIndex": "1.67", "options": "1.67 비구면", "sellingPrice": "15,000", "status": "사용"},
  {"brand": "케미", "unitType": "안경렌즈 여벌", "productType": "안경렌즈 여벌", "productName": "[케미 아토메가] 1.74 ASP", "mainProductName": "아토메가", "refractiveIndex": "1.74", "options": "1.74 비구면", "sellingPrice": "28,500", "status": "사용"},
  {"brand": "케미", "unitType": "안경렌즈 여벌", "productType": "안경렌즈 여벌", "productName": "[케미 양면비구면] 1.61 ASP", "mainProductName": "양면비구면 D-FREE", "refractiveIndex": "1.60", "options": "1.60 양면비구면 PUV", "sellingPrice": "6,000", "status": "사용"},
  {"brand": "케미", "unitType": "안경렌즈 여벌", "productType": "안경렌즈 여벌", "productName": "[케미 양면비구면] 1.67 ASP", "mainProductName": "양면비구면 D-FREE", "refractiveIndex": "1.67", "options": "1.67 양면비구면 PUV", "sellingPrice": "9,500", "status": "사용"},
  {"brand": "케미", "unitType": "안경렌즈 여벌", "productType": "안경렌즈 여벌", "productName": "[케미 양면비구면] 1.74 ASP", "mainProductName": "양면비구면 D-FREE", "refractiveIndex": "1.74", "options": "1.74 양면비구면 PUV", "sellingPrice": "22,500", "status": "사용"},
  {"brand": "케미", "unitType": "안경렌즈 여벌", "productType": "안경렌즈 여벌", "productName": "[케미 양면비구면] 1.74 클리어", "mainProductName": "양면비구면 D-FREE", "refractiveIndex": "1.74", "options": "1.74 클리어 PUV", "sellingPrice": "22,500", "status": "사용"},
  {"brand": "케미", "unitType": "안경렌즈 여벌", "productType": "안경렌즈 여벌", "productName": "[케미 완전밀러] 고트 (골드)", "mainProductName": "완전밀러", "refractiveIndex": "1.60", "options": "1.60 하이커브 골드", "sellingPrice": "11,000", "status": "사용"},
  {"brand": "케미", "unitType": "안경렌즈 여벌", "productType": "안경렌즈 여벌", "productName": "[케미 완전밀러] 고트 (그린)", "mainProductName": "완전밀러", "refractiveIndex": "1.60", "options": "1.60 하이커브 그린", "sellingPrice": "11,000", "status": "사용"},
  {"brand": "케미", "unitType": "안경렌즈 여벌", "productType": "안경렌즈 여벌", "productName": "[케미 완전밀러] 고트 (레드)", "mainProductName": "완전밀러", "refractiveIndex": "1.60", "options": "1.60 하이커브 레드", "sellingPrice": "11,000", "status": "사용"},
  {"brand": "케미", "unitType": "안경렌즈 여벌", "productType": "안경렌즈 여벌", "productName": "[케미 완전밀러] 고트 (블루)", "mainProductName": "완전밀러", "refractiveIndex": "1.60", "options": "1.60 하이커브 블루", "sellingPrice": "11,000", "status": "사용"},
  {"brand": "케미", "unitType": "안경렌즈 여벌", "productType": "안경렌즈 여벌", "productName": "[케미 완전밀러] 고트 (실버)", "mainProductName": "완전밀러", "refractiveIndex": "1.60", "options": "1.60 하이커브 실버", "sellingPrice": "11,000", "status": "사용"},
  {"brand": "케미", "unitType": "안경렌즈 여벌", "productType": "안경렌즈 여벌", "productName": "[케미 완전밀러] 중트 (골드)", "mainProductName": "완전밀러", "refractiveIndex": "1.56", "options": "1.56 하이커브 골드", "sellingPrice": "7,250", "status": "사용"},
  {"brand": "케미", "unitType": "안경렌즈 여벌", "productType": "안경렌즈 여벌", "productName": "[케미 완전밀러] 중트 (그린)", "mainProductName": "완전밀러", "refractiveIndex": "1.56", "options": "1.56 하이커브 그린", "sellingPrice": "7,250", "status": "사용"},
  {"brand": "케미", "unitType": "안경렌즈 여벌", "productType": "안경렌즈 여벌", "productName": "[케미 완전밀러] 중트 (레드)", "mainProductName": "완전밀러", "refractiveIndex": "1.56", "options": "1.56 하이커브 레드", "sellingPrice": "7,250", "status": "사용"},
  {"brand": "케미", "unitType": "안경렌즈 여벌", "productType": "안경렌즈 여벌", "productName": "[케미 완전밀러] 중트 (블루)", "mainProductName": "완전밀러", "refractiveIndex": "1.56", "options": "1.56 하이커브 블루", "sellingPrice": "7,250", "status": "사용"},
  {"brand": "케미", "unitType": "안경렌즈 여벌", "productType": "안경렌즈 여벌", "productName": "[케미 완전밀러] 중트 (실버)", "mainProductName": "완전밀러", "refractiveIndex": "1.56", "options": "1.56 하이커브 실버", "sellingPrice": "7,250", "status": "사용"},
  {"brand": "케미", "unitType": "안경렌즈 여벌", "productType": "안경렌즈 여벌", "productName": "[케미 일반] 고", "mainProductName": "일반멀티", "refractiveIndex": "1.60", "options": "고", "sellingPrice": "3,600", "status": "사용"},
  {"brand": "케미", "unitType": "안경렌즈 여벌", "productType": "안경렌즈 여벌", "productName": "[케미 일반] 고 70파이 (+)", "mainProductName": "일반멀티", "refractiveIndex": "1.60", "options": "고 70파이 (+)", "sellingPrice": "3,600", "status": "사용"},
  {"brand": "케미", "unitType": "안경렌즈 여벌", "productType": "안경렌즈 여벌", "productName": "[케미 일반] 고비", "mainProductName": "일반멀티", "refractiveIndex": "1.60", "options": "고비", "sellingPrice": "4,250", "status": "사용"},
  {"brand": "케미", "unitType": "안경렌즈 여벌", "productType": "안경렌즈 여벌", "productName": "[케미 일반] 고비 60파이 (+)", "mainProductName": "일반멀티", "refractiveIndex": "1.60", "options": "고비 60파이", "sellingPrice": "7,500", "status": "사용"},
  {"brand": "케미", "unitType": "안경렌즈 여벌", "productType": "안경렌즈 여벌", "productName": "[케미 일반] 중", "mainProductName": "일반멀티", "refractiveIndex": "1.56", "options": "중", "sellingPrice": "1,750", "status": "사용"},
  {"brand": "케미", "unitType": "안경렌즈 여벌", "productType": "안경렌즈 여벌", "productName": "[케미 일반] 중비", "mainProductName": "일반멀티", "refractiveIndex": "1.56", "options": "중비", "sellingPrice": "2,900", "status": "사용"},
  {"brand": "케미", "unitType": "안경렌즈 여벌", "productType": "안경렌즈 여벌", "productName": "[케미 일반] 초고비", "mainProductName": "일반멀티", "refractiveIndex": "1.67", "options": "초고비", "sellingPrice": "5,750", "status": "사용"},
  {"brand": "케미", "unitType": "안경렌즈 여벌", "productType": "안경렌즈 여벌", "productName": "[케미 초발수] 1.74", "mainProductName": "초발수", "refractiveIndex": "1.74", "options": "1.74", "sellingPrice": "14,000", "status": "사용"},
  {"brand": "케미", "unitType": "안경렌즈 여벌", "productType": "안경렌즈 여벌", "productName": "[케미 초발수] 고", "mainProductName": "초발수", "refractiveIndex": "1.60", "options": "고", "sellingPrice": "4,100", "status": "사용"},
  {"brand": "케미", "unitType": "안경렌즈 여벌", "productType": "안경렌즈 여벌", "productName": "[케미 초발수] 고비", "mainProductName": "초발수", "refractiveIndex": "1.60", "options": "고비", "sellingPrice": "4,750", "status": "사용"},
  {"brand": "케미", "unitType": "안경렌즈 여벌", "productType": "안경렌즈 여벌", "productName": "[케미 초발수] 중", "mainProductName": "초발수", "refractiveIndex": "1.56", "options": "중", "sellingPrice": "2,750", "status": "사용"},
  {"brand": "케미", "unitType": "안경렌즈 여벌", "productType": "안경렌즈 여벌", "productName": "[케미 초발수] 중비", "mainProductName": "초발수", "refractiveIndex": "1.56", "options": "중비", "sellingPrice": "3,465", "status": "사용"},
  {"brand": "케미", "unitType": "안경렌즈 여벌", "productType": "안경렌즈 여벌", "productName": "[케미 초발수] 초고비", "mainProductName": "초발수", "refractiveIndex": "1.67", "options": "초고비", "sellingPrice": "6,000", "status": "사용"},
  {"brand": "케미", "unitType": "안경렌즈 여벌", "productType": "안경렌즈 여벌", "productName": "[케미 퍼펙트] 1.74", "mainProductName": "퍼펙트UV", "refractiveIndex": "1.74", "options": "1.74", "sellingPrice": "12,500", "status": "사용"},
  {"brand": "케미", "unitType": "안경렌즈 여벌", "productType": "안경렌즈 여벌", "productName": "[케미 퍼펙트] 고", "mainProductName": "퍼펙트UV", "refractiveIndex": "1.60", "options": "고", "sellingPrice": "4,450", "status": "사용"},
  {"brand": "케미", "unitType": "안경렌즈 여벌", "productType": "안경렌즈 여벌", "productName": "[케미 퍼펙트] 고비", "mainProductName": "퍼펙트UV", "refractiveIndex": "1.60", "options": "고비", "sellingPrice": "5,500", "status": "사용"},
  {"brand": "케미", "unitType": "안경렌즈 여벌", "productType": "안경렌즈 여벌", "productName": "[케미 퍼펙트] 중", "mainProductName": "퍼펙트UV", "refractiveIndex": "1.56", "options": "중", "sellingPrice": "2,250", "status": "사용"},
  {"brand": "케미", "unitType": "안경렌즈 여벌", "productType": "안경렌즈 여벌", "productName": "[케미 퍼펙트] 중비", "mainProductName": "퍼펙트UV", "refractiveIndex": "1.56", "options": "중비", "sellingPrice": "2,750", "status": "사용"},
  {"brand": "케미", "unitType": "안경렌즈 여벌", "productType": "안경렌즈 여벌", "productName": "[케미 퍼펙트] 초고비", "mainProductName": "퍼펙트UV", "refractiveIndex": "1.67", "options": "초고비", "sellingPrice": "6,750", "status": "사용"}
]
